manitest/__init__.py
manitest/base.py
manitest/eval.py
manitest/main.py
manitest/metrics.py
manitest/task_template.py
manitest/tasks/mednli.py
manitest/tasks/mednli_fewshot.py
manitest/tasks/scitail.py
manitest/utils.py
manitest-0.1.2.dist-info/LICENSE
manitest-0.1.2.dist-info/METADATA
manitest-0.1.2.dist-info/WHEEL
manitest-0.1.2.dist-info/RECORD
