Metadata-Version: 2.1
Name: manitest
Version: 0.1.2
Summary: An LLM evaluation harness built with Manifest + EleutherAI
License: MIT
Author: Michael Wornow
Requires-Python: >=3.9
Classifier: License :: OSI Approved :: MIT License
Classifier: Programming Language :: Python :: 3
Classifier: Programming Language :: Python :: 3.9
Classifier: Programming Language :: Python :: 3.10
Classifier: Programming Language :: Python :: 3.11
Requires-Dist: datasets (==2.10.1)
Requires-Dist: loguru (==0.6.0)
Requires-Dist: protobuf (==3.20)
Requires-Dist: rouge-score (==0.1.2)
Requires-Dist: scikit-learn (==1.2.2)
